haasomeapi/HaasomeClient.py
haasomeapi/__init__.py
haasomeapi/apis/AccountDataApi.py
haasomeapi/apis/AdvancedOrderApi.py
haasomeapi/apis/ApiBase.py
haasomeapi/apis/CustomBotApi.py
haasomeapi/apis/MarketDataApi.py
haasomeapi/apis/TradeApi.py
haasomeapi/apis/TradeBotApi.py
haasomeapi/apis/__init__.py
haasomeapi/dataobjects/__init__.py
haasomeapi/dataobjects/accountdata/AccountInformation.py
haasomeapi/dataobjects/accountdata/BaseOrder.py
haasomeapi/dataobjects/accountdata/OrderContainer.py
haasomeapi/dataobjects/accountdata/Position.py
haasomeapi/dataobjects/accountdata/SoftwareInformation.py
haasomeapi/dataobjects/accountdata/Wallet.py
haasomeapi/dataobjects/accountdata/__init__.py
haasomeapi/dataobjects/advancedorders/AdvancedOrderBase.py
haasomeapi/dataobjects/advancedorders/StopTakeProfitOrder.py
haasomeapi/dataobjects/advancedorders/TrailingStop.py
haasomeapi/dataobjects/advancedorders/__init__.py
haasomeapi/dataobjects/custombots/AccumulationBot.py
haasomeapi/dataobjects/custombots/AdvancedIndexBot.py
haasomeapi/dataobjects/custombots/BaseCustomBot.py
haasomeapi/dataobjects/custombots/CryptoIndexBot.py
haasomeapi/dataobjects/custombots/EmailBot.py
haasomeapi/dataobjects/custombots/FlashCrashBot.py
haasomeapi/dataobjects/custombots/InterExchangeArbitrageBot.py
haasomeapi/dataobjects/custombots/MadHatterBot.py
haasomeapi/dataobjects/custombots/MarketMakingBot.py
haasomeapi/dataobjects/custombots/OrderBot.py
haasomeapi/dataobjects/custombots/ScalperBot.py
haasomeapi/dataobjects/custombots/ScriptBot.py
haasomeapi/dataobjects/custombots/ZoneRecoveryBot.py
haasomeapi/dataobjects/custombots/__init__.py
haasomeapi/dataobjects/custombots/dataobjects/AdvancedIndexBotIndex.py
haasomeapi/dataobjects/custombots/dataobjects/AdvancedIndexBotIndexSaveObject.py
haasomeapi/dataobjects/custombots/dataobjects/CryptoIndexBotIndex.py
haasomeapi/dataobjects/custombots/dataobjects/CryptoIndexBotIndexResult.py
haasomeapi-3.2.4.1.dist-info/LICENSE
haasomeapi-3.2.4.1.dist-info/METADATA
haasomeapi-3.2.4.1.dist-info/WHEEL
haasomeapi-3.2.4.1.dist-info/top_level.txt
haasomeapi-3.2.4.1.dist-info/RECORD
