Metadata-Version: 2.1
Name: haasomeapi
Version: 3.2.4.1
Summary: Python module to interact with the Haasonline Local API
Home-page: http://github.com/haasome-tools/haasomeapi
Author: Haasome Tools
Author-email: haasomeapi@haasometools.com
License: MIT
Platform: UNKNOWN
Requires-Dist: requests
Requires-Dist: python-dateutil
